Metadata-Version: 1.2
Name: slackelot
Version: 0.0.3
Summary: A simple wrapper around the Slack web api to post messages
Home-page: https://github.com/Chris-Graffagnino/slackelot
Author: Chris Graffagnino
Author-email: graffwebdev@gmail.com
License: MIT
Keywords: slack
Platform: UNKNOWN
Classifier: Development Status :: 3 - Alpha
Classifier: Intended Audience :: Developers
Classifier: License :: OSI Approved :: MIT License
Classifier: Natural Language :: English
Classifier: Operating System :: OS Independent
Classifier: Programming Language :: Python :: 2
Classifier: Programming Language :: Python :: 2.7
Classifier: Programming Language :: Python :: 3
Classifier: Programming Language :: Python :: 3.3
Classifier: Programming Language :: Python :: 3.4
Classifier: Programming Language :: Python :: 3.5
Classifier: Programming Language :: Python :: 3.6
Classifier: Topic :: Software Development :: Libraries :: Python Modules
Requires-Python: >=2.7
